gpp_cpass_decrypt/__init__.py
gpp_cpass_decrypt/__main__.py
gpp_cpass_decrypt-0.0.1.dist-info/LICENSE
gpp_cpass_decrypt-0.0.1.dist-info/METADATA
gpp_cpass_decrypt-0.0.1.dist-info/WHEEL
gpp_cpass_decrypt-0.0.1.dist-info/entry_points.txt
gpp_cpass_decrypt-0.0.1.dist-info/top_level.txt
gpp_cpass_decrypt-0.0.1.dist-info/RECORD
