Metadata-Version: 2.1
Name: gpp-cpass-decrypt
Version: 0.0.1
Summary: Python tool that decrypts credentials stored in Group Policy Preferences (GPP) files (Groups.xml) located in the SYSVOL folder.
Home-page: https://gpp-cpass-decrypt.hackem.org
Author: Galoget Latorre
Project-URL: Homepage, https://gpp-cpass-decrypt.hackem.org
Project-URL: Source, https://github.com/galoget/gpp-cpass-decrypt
Project-URL: Bug_Tracker, https://github.com/galoget/gpp-cpass-decrypt/issues
Project-URL: Facebook, https://www.facebook.com/hackem.epn
Project-URL: Twitter, https://twitter.com/hackem
Project-URL: LinkedIn, https://linkedin.com/company/hackem
Project-URL: Instagram, https://instagram.com/hackemcorp
Project-URL: YouTube, https://youtube.com/hackemcorp
Project-URL: Telegram, https://t.me/hackemSecurity
Project-URL: Twitch, https://twitch.com/hackemcorp
Keywords: python,active-directory,python-script,python3,windows-server,aes-encryption,decryption,group-policy,decrypter,gpp,crypto,ethical-hacking,red-team,cpassword,gpp-decrypt,domain-security,cpassword-attribute,active-directory-exploitation,cpass,group-policy-preferences,microsoft-windows-server,active-directory-security,cryptography
Classifier: License :: OSI Approved :: GNU General Public License v2 (GPLv2)
Classifier: Programming Language :: Python
Classifier: Programming Language :: Python :: 3
Classifier: Programming Language :: Python :: 3.2
Classifier: Programming Language :: Python :: 3.3
Classifier: Programming Language :: Python :: 3.4
Classifier: Programming Language :: Python :: 3.5
Classifier: Programming Language :: Python :: 3.6
Classifier: Programming Language :: Python :: 3.7
Classifier: Programming Language :: Python :: 3.8
Classifier: Programming Language :: Python :: 3.9
Classifier: Programming Language :: Python :: 3.10
Classifier: Development Status :: 5 - Production/Stable
Classifier: Environment :: Console
Classifier: Intended Audience :: Developers
Classifier: Intended Audience :: Education
Classifier: Intended Audience :: Information Technology
Classifier: Intended Audience :: Science/Research
Classifier: Intended Audience :: System Administrators
Classifier: Natural Language :: English
Classifier: Operating System :: OS Independent
Classifier: Topic :: Software Development :: Libraries :: Python Modules
Classifier: Topic :: Security :: Cryptography
Requires-Python: >=3.2
License-File: LICENSE
Requires-Dist: colorama (>=0.4.4)
Requires-Dist: pycryptodome (>=3.14.1)
